{
  "version": "0.3.3",
  "flags": {},
  "shapes": [
    {
      "label": "1",
      "text": "",
      "points": [
        [
          274.0,
          290.0
        ],
        [
          254.0,
          289.0
        ],
        [
          239.0,
          302.0
        ],
        [
          239.0,
          309.0
        ],
        [
          230.0,
          315.0
        ],
        [
          231.0,
          332.0
        ],
        [
          228.0,
          338.0
        ],
        [
          231.0,
          353.0
        ],
        [
          237.0,
          362.0
        ],
        [
          229.0,
          363.0
        ],
        [
          214.0,
          378.0
        ],
        [
          200.0,
          384.0
        ],
        [
          172.0,
          406.0
        ],
        [
          148.0,
          451.0
        ],
        [
          141.0,
          471.0
        ],
        [
          141.0,
          483.0
        ],
        [
          152.0,
          497.0
        ],
        [
          162.0,
          542.0
        ],
        [
          153.0,
          588.0
        ],
        [
          150.0,
          704.0
        ],
        [
          119.0,
          841.0
        ],
        [
          120.0,
          853.0
        ],
        [
          115.0,
          871.0
        ],
        [
          117.0,
          880.0
        ],
        [
          124.0,
          883.0
        ],
        [
          140.0,
          882.0
        ],
        [
          143.0,
          879.0
        ],
        [
          142.0,
          859.0
        ],
        [
          158.0,
          848.0
        ],
        [
          162.0,
          825.0
        ],
        [
          175.0,
          803.0
        ],
        [
          182.0,
          770.0
        ],
        [
          193.0,
          749.0
        ],
        [
          198.0,
          768.0
        ],
        [
          202.0,
          837.0
        ],
        [
          209.0,
          867.0
        ],
        [
          207.0,
          877.0
        ],
        [
          209.0,
          888.0
        ],
        [
          220.0,
          895.0
        ],
        [
          262.0,
          896.0
        ],
        [
          281.0,
          893.0
        ],
        [
          287.0,
          887.0
        ],
        [
          283.0,
          879.0
        ],
        [
          265.0,
          873.0
        ],
        [
          252.0,
          862.0
        ],
        [
          249.0,
          849.0
        ],
        [
          241.0,
          835.0
        ],
        [
          240.0,
          824.0
        ],
        [
          241.0,
          745.0
        ],
        [
          244.0,
          737.0
        ],
        [
          241.0,
          694.0
        ],
        [
          246.0,
          647.0
        ],
        [
          258.0,
          598.0
        ],
        [
          260.0,
          596.0
        ],
        [
          271.0,
          601.0
        ],
        [
          272.0,
          608.0
        ],
        [
          279.0,
          612.0
        ],
        [
          282.0,
          608.0
        ],
        [
          281.0,
          603.0
        ],
        [
          288.0,
          595.0
        ],
        [
          297.0,
          553.0
        ],
        [
          300.0,
          520.0
        ],
        [
          296.0,
          421.0
        ],
        [
          281.0,
          392.0
        ],
        [
          290.0,
          392.0
        ],
        [
          296.0,
          385.0
        ],
        [
          309.0,
          345.0
        ],
        [
          309.0,
          332.0
        ],
        [
          296.0,
          306.0
        ]
      ],
      "group_id": null,
      "shape_type": "polygon",
      "flags": {}
    },
    {
      "label": "2",
      "text": "",
      "points": [
        [
          466.0,
          523.0
        ],
        [
          465.0,
          536.0
        ],
        [
          482.0,
          548.0
        ],
        [
          483.0,
          573.0
        ],
        [
          514.0,
          624.0
        ],
        [
          513.0,
          694.0
        ],
        [
          532.0,
          806.0
        ],
        [
          529.0,
          877.0
        ],
        [
          545.0,
          872.0
        ],
        [
          553.0,
          850.0
        ],
        [
          554.0,
          780.0
        ],
        [
          560.0,
          792.0
        ],
        [
          563.0,
          859.0
        ],
        [
          569.0,
          873.0
        ],
        [
          578.0,
          872.0
        ],
        [
          576.0,
          816.0
        ],
        [
          584.0,
          783.0
        ],
        [
          595.0,
          778.0
        ],
        [
          608.0,
          804.0
        ],
        [
          603.0,
          906.0
        ],
        [
          607.0,
          933.0
        ],
        [
          618.0,
          936.0
        ],
        [
          622.0,
          930.0
        ],
        [
          624.0,
          873.0
        ],
        [
          638.0,
          799.0
        ],
        [
          671.0,
          830.0
        ],
        [
          674.0,
          928.0
        ],
        [
          686.0,
          933.0
        ],
        [
          704.0,
          798.0
        ],
        [
          710.0,
          806.0
        ],
        [
          714.0,
          847.0
        ],
        [
          697.0,
          955.0
        ],
        [
          699.0,
          994.0
        ],
        [
          714.0,
          997.0
        ],
        [
          719.0,
          992.0
        ],
        [
          720.0,
          932.0
        ],
        [
          743.0,
          858.0
        ],
        [
          750.0,
          855.0
        ],
        [
          769.0,
          868.0
        ],
        [
          769.0,
          909.0
        ],
        [
          780.0,
          925.0
        ],
        [
          793.0,
          917.0
        ],
        [
          791.0,
          865.0
        ],
        [
          798.0,
          859.0
        ],
        [
          810.0,
          866.0
        ],
        [
          825.0,
          861.0
        ],
        [
          829.0,
          916.0
        ],
        [
          851.0,
          1014.0
        ],
        [
          859.0,
          1021.0
        ],
        [
          876.0,
          1021.0
        ],
        [
          886.0,
          1014.0
        ],
        [
          869.0,
          978.0
        ],
        [
          862.0,
          945.0
        ],
        [
          874.0,
          897.0
        ],
        [
          875.0,
          857.0
        ],
        [
          880.0,
          852.0
        ],
        [
          941.0,
          852.0
        ],
        [
          955.0,
          889.0
        ],
        [
          955.0,
          922.0
        ],
        [
          935.0,
          948.0
        ],
        [
          936.0,
          957.0
        ],
        [
          944.0,
          955.0
        ],
        [
          937.0,
          992.0
        ],
        [
          949.0,
          997.0
        ],
        [
          968.0,
          994.0
        ],
        [
          984.0,
          1019.0
        ],
        [
          1009.0,
          1022.0
        ],
        [
          1019.0,
          1017.0
        ],
        [
          1019.0,
          1003.0
        ],
        [
          998.0,
          956.0
        ],
        [
          984.0,
          869.0
        ],
        [
          990.0,
          844.0
        ],
        [
          1019.0,
          825.0
        ],
        [
          1020.0,
          579.0
        ],
        [
          997.0,
          584.0
        ],
        [
          975.0,
          602.0
        ],
        [
          973.0,
          616.0
        ],
        [
          915.0,
          592.0
        ],
        [
          888.0,
          591.0
        ],
        [
          866.0,
          598.0
        ],
        [
          838.0,
          620.0
        ],
        [
          834.0,
          647.0
        ],
        [
          829.0,
          643.0
        ],
        [
          832.0,
          620.0
        ],
        [
          814.0,
          583.0
        ],
        [
          774.0,
          553.0
        ],
        [
          732.0,
          545.0
        ],
        [
          683.0,
          482.0
        ],
        [
          660.0,
          488.0
        ],
        [
          614.0,
          523.0
        ],
        [
          614.0,
          536.0
        ],
        [
          622.0,
          546.0
        ],
        [
          644.0,
          553.0
        ],
        [
          656.0,
          566.0
        ],
        [
          670.0,
          607.0
        ],
        [
          574.0,
          579.0
        ],
        [
          565.0,
          567.0
        ],
        [
          563.0,
          541.0
        ],
        [
          572.0,
          535.0
        ],
        [
          575.0,
          519.0
        ],
        [
          546.0,
          501.0
        ],
        [
          510.0,
          496.0
        ]
      ],
      "group_id": null,
      "shape_type": "polygon",
      "flags": {}
    },
    {
      "label": "3",
      "text": "",
      "points": [
        [
          0.0,
          555.0
        ],
        [
          0.0,
          901.0
        ],
        [
          7.0,
          905.0
        ],
        [
          12.0,
          906.0
        ],
        [
          27.0,
          906.0
        ],
        [
          31.0,
          902.0
        ],
        [
          31.0,
          872.0
        ],
        [
          33.0,
          865.0
        ],
        [
          39.0,
          858.0
        ],
        [
          46.0,
          842.0
        ],
        [
          51.0,
          837.0
        ],
        [
          55.0,
          829.0
        ],
        [
          62.0,
          823.0
        ],
        [
          65.0,
          825.0
        ],
        [
          67.0,
          838.0
        ],
        [
          66.0,
          857.0
        ],
        [
          68.0,
          871.0
        ],
        [
          73.0,
          873.0
        ],
        [
          78.0,
          868.0
        ],
        [
          79.0,
          861.0
        ],
        [
          77.0,
          846.0
        ],
        [
          78.0,
          817.0
        ],
        [
          84.0,
          807.0
        ],
        [
          102.0,
          791.0
        ],
        [
          108.0,
          780.0
        ],
        [
          115.0,
          771.0
        ],
        [
          116.0,
          740.0
        ],
        [
          115.0,
          739.0
        ],
        [
          114.0,
          694.0
        ],
        [
          112.0,
          677.0
        ],
        [
          109.0,
          671.0
        ],
        [
          107.0,
          660.0
        ],
        [
          99.0,
          639.0
        ],
        [
          90.0,
          623.0
        ],
        [
          69.0,
          604.0
        ],
        [
          50.0,
          601.0
        ],
        [
          42.0,
          597.0
        ],
        [
          38.0,
          593.0
        ],
        [
          34.0,
          577.0
        ],
        [
          27.0,
          566.0
        ],
        [
          14.0,
          557.0
        ],
        [
          8.0,
          555.0
        ]
      ],
      "group_id": null,
      "shape_type": "polygon",
      "flags": {}
    },
    {
      "label": "4",
      "text": "",
      "points": [
        [
          108.0,
          265.0
        ],
        [
          99.0,
          267.0
        ],
        [
          91.0,
          279.0
        ],
        [
          90.0,
          307.0
        ],
        [
          87.0,
          318.0
        ],
        [
          79.0,
          327.0
        ],
        [
          69.0,
          329.0
        ],
        [
          59.0,
          337.0
        ],
        [
          53.0,
          349.0
        ],
        [
          52.0,
          380.0
        ],
        [
          47.0,
          387.0
        ],
        [
          45.0,
          397.0
        ],
        [
          45.0,
          406.0
        ],
        [
          51.0,
          419.0
        ],
        [
          48.0,
          452.0
        ],
        [
          49.0,
          495.0
        ],
        [
          46.0,
          509.0
        ],
        [
          46.0,
          518.0
        ],
        [
          48.0,
          530.0
        ],
        [
          52.0,
          537.0
        ],
        [
          52.0,
          543.0
        ],
        [
          55.0,
          550.0
        ],
        [
          61.0,
          588.0
        ],
        [
          64.0,
          594.0
        ],
        [
          83.0,
          611.0
        ],
        [
          96.0,
          626.0
        ],
        [
          103.0,
          639.0
        ],
        [
          114.0,
          671.0
        ],
        [
          118.0,
          698.0
        ],
        [
          118.0,
          725.0
        ],
        [
          121.0,
          765.0
        ],
        [
          123.0,
          767.0
        ],
        [
          127.0,
          767.0
        ],
        [
          134.0,
          749.0
        ],
        [
          147.0,
          693.0
        ],
        [
          147.0,
          653.0
        ],
        [
          150.0,
          610.0
        ],
        [
          149.0,
          587.0
        ],
        [
          154.0,
          567.0
        ],
        [
          155.0,
          530.0
        ],
        [
          153.0,
          518.0
        ],
        [
          149.0,
          512.0
        ],
        [
          145.0,
          497.0
        ],
        [
          139.0,
          488.0
        ],
        [
          138.0,
          475.0
        ],
        [
          146.0,
          449.0
        ],
        [
          165.0,
          416.0
        ],
        [
          168.0,
          406.0
        ],
        [
          168.0,
          396.0
        ],
        [
          160.0,
          341.0
        ],
        [
          153.0,
          329.0
        ],
        [
          136.0,
          314.0
        ],
        [
          136.0,
          278.0
        ],
        [
          126.0,
          266.0
        ]
      ],
      "group_id": null,
      "shape_type": "polygon",
      "flags": {}
    },
    {
      "label": "4",
      "text": "",
      "points": [
        [
          209.0,
          221.0
        ],
        [
          204.0,
          221.0
        ],
        [
          200.0,
          224.0
        ],
        [
          198.0,
          224.0
        ],
        [
          197.0,
          223.0
        ],
        [
          193.0,
          223.0
        ],
        [
          194.0,
          225.0
        ],
        [
          200.0,
          225.0
        ],
        [
          204.0,
          229.0
        ],
        [
          204.0,
          230.0
        ],
        [
          200.0,
          232.0
        ],
        [
          193.0,
          232.0
        ],
        [
          185.0,
          239.0
        ],
        [
          185.0,
          243.0
        ],
        [
          184.0,
          244.0
        ],
        [
          184.0,
          250.0
        ],
        [
          187.0,
          255.0
        ],
        [
          187.0,
          267.0
        ],
        [
          185.0,
          269.0
        ],
        [
          138.82926829268303,
          277.8536585365854
        ],
        [
          136.39024390243907,
          254.68292682926833
        ],
        [
          184.0,
          281.0
        ],
        [
          138.82926829268303,
          268.0975609756098
        ],
        [
          183.0,
          285.0
        ],
        [
          149.8048780487805,
          264.43902439024396
        ],
        [
          141.26829268292687,
          321.75609756097566
        ],
        [
          138.82926829268303,
          320.5365853658537
        ],
        [
          152.24390243902445,
          321.75609756097566
        ],
        [
          180.0,
          318.0
        ],
        [
          179.0,
          318.0
        ],
        [
          144.9268292682927,
          326.63414634146346
        ],
        [
          169.0,
          325.0
        ],
        [
          167.0,
          327.0
        ],
        [
          166.0,
          331.0
        ],
        [
          165.0,
          332.0
        ],
        [
          165.0,
          356.0
        ],
        [
          166.0,
          357.0
        ],
        [
          166.0,
          364.0
        ],
        [
          167.0,
          365.0
        ],
        [
          167.0,
          373.0
        ],
        [
          168.0,
          374.0
        ],
        [
          168.0,
          380.0
        ],
        [
          169.0,
          381.0
        ],
        [
          169.0,
          388.0
        ],
        [
          170.0,
          389.0
        ],
        [
          170.0,
          393.0
        ],
        [
          171.0,
          395.0
        ],
        [
          175.0,
          399.0
        ],
        [
          175.0,
          400.0
        ],
        [
          181.0,
          397.0
        ],
        [
          193.0,
          386.0
        ],
        [
          208.0,
          379.0
        ],
        [
          210.0,
          377.0
        ],
        [
          214.0,
          375.0
        ],
        [
          220.0,
          368.0
        ],
        [
          222.0,
          364.0
        ],
        [
          222.0,
          350.0
        ],
        [
          223.0,
          349.0
        ],
        [
          223.0,
          329.0
        ],
        [
          224.0,
          328.0
        ],
        [
          224.0,
          325.0
        ],
        [
          225.0,
          324.0
        ],
        [
          225.0,
          321.0
        ],
        [
          226.0,
          320.0
        ],
        [
          227.0,
          312.0
        ],
        [
          228.0,
          311.0
        ],
        [
          228.0,
          309.0
        ],
        [
          229.0,
          308.0
        ],
        [
          230.0,
          304.0
        ],
        [
          236.0,
          298.0
        ],
        [
          240.0,
          296.0
        ],
        [
          246.0,
          289.0
        ],
        [
          248.0,
          285.0
        ],
        [
          250.0,
          277.0
        ],
        [
          251.0,
          276.0
        ],
        [
          251.0,
          272.0
        ],
        [
          252.0,
          271.0
        ],
        [
          252.0,
          268.0
        ],
        [
          253.0,
          267.0
        ],
        [
          253.0,
          253.0
        ],
        [
          252.0,
          252.0
        ],
        [
          252.0,
          250.0
        ],
        [
          249.0,
          247.0
        ],
        [
          241.0,
          243.0
        ],
        [
          237.0,
          243.0
        ],
        [
          236.0,
          242.0
        ],
        [
          232.0,
          242.0
        ],
        [
          231.0,
          241.0
        ],
        [
          223.0,
          241.0
        ],
        [
          222.0,
          242.0
        ],
        [
          215.0,
          243.0
        ],
        [
          212.0,
          245.0
        ],
        [
          211.0,
          245.0
        ],
        [
          209.0,
          243.0
        ],
        [
          209.0,
          240.0
        ],
        [
          212.0,
          236.0
        ],
        [
          211.0,
          233.0
        ],
        [
          208.0,
          230.0
        ],
        [
          208.0,
          229.0
        ],
        [
          211.0,
          226.0
        ],
        [
          211.0,
          223.0
        ]
      ],
      "group_id": null,
      "shape_type": "polygon",
      "flags": {}
    },
    {
      "label": "4",
      "text": "",
      "points": [
        [
          852.0,
          221.0
        ],
        [
          814.0,
          198.0
        ],
        [
          804.0,
          198.0
        ],
        [
          786.0,
          215.0
        ],
        [
          780.0,
          213.0
        ],
        [
          775.0,
          243.0
        ],
        [
          764.0,
          265.0
        ],
        [
          753.0,
          271.0
        ],
        [
          766.0,
          277.0
        ],
        [
          765.0,
          291.0
        ],
        [
          751.0,
          304.0
        ],
        [
          743.0,
          301.0
        ],
        [
          740.0,
          309.0
        ],
        [
          732.0,
          300.0
        ],
        [
          730.0,
          309.0
        ],
        [
          708.0,
          315.0
        ],
        [
          706.0,
          322.0
        ],
        [
          714.0,
          333.0
        ],
        [
          698.0,
          321.0
        ],
        [
          700.0,
          275.0
        ],
        [
          711.0,
          268.0
        ],
        [
          712.0,
          260.0
        ],
        [
          702.0,
          245.0
        ],
        [
          685.0,
          236.0
        ],
        [
          659.0,
          238.0
        ],
        [
          648.0,
          247.0
        ],
        [
          658.0,
          317.0
        ],
        [
          644.0,
          344.0
        ],
        [
          625.0,
          314.0
        ],
        [
          631.0,
          308.0
        ],
        [
          639.0,
          259.0
        ],
        [
          637.0,
          225.0
        ],
        [
          625.0,
          212.0
        ],
        [
          601.0,
          213.0
        ],
        [
          594.0,
          238.0
        ],
        [
          578.0,
          229.0
        ],
        [
          551.0,
          233.0
        ],
        [
          541.0,
          271.0
        ],
        [
          547.0,
          290.0
        ],
        [
          542.0,
          288.0
        ],
        [
          543.0,
          305.0
        ],
        [
          526.0,
          329.0
        ],
        [
          523.0,
          344.0
        ],
        [
          517.0,
          333.0
        ],
        [
          505.0,
          333.0
        ],
        [
          492.0,
          319.0
        ],
        [
          516.0,
          293.0
        ],
        [
          517.0,
          258.0
        ],
        [
          512.0,
          247.0
        ],
        [
          491.0,
          242.0
        ],
        [
          477.0,
          258.0
        ],
        [
          450.0,
          255.0
        ],
        [
          433.0,
          263.0
        ],
        [
          429.0,
          301.0
        ],
        [
          435.0,
          331.0
        ],
        [
          407.0,
          345.0
        ],
        [
          381.0,
          397.0
        ],
        [
          390.0,
          424.0
        ],
        [
          385.0,
          531.0
        ],
        [
          390.0,
          551.0
        ],
        [
          404.0,
          542.0
        ],
        [
          410.0,
          567.0
        ],
        [
          410.0,
          682.0
        ],
        [
          427.0,
          769.0
        ],
        [
          424.0,
          788.0
        ],
        [
          441.0,
          789.0
        ],
        [
          467.0,
          775.0
        ],
        [
          479.0,
          756.0
        ],
        [
          481.0,
          707.0
        ],
        [
          490.0,
          799.0
        ],
        [
          512.0,
          801.0
        ],
        [
          524.0,
          789.0
        ],
        [
          509.0,
          692.0
        ],
        [
          510.0,
          630.0
        ],
        [
          502.0,
          609.0
        ],
        [
          481.0,
          585.0
        ],
        [
          479.0,
          554.0
        ],
        [
          468.0,
          548.0
        ],
        [
          465.0,
          538.0
        ],
        [
          469.0,
          516.0
        ],
        [
          509.0,
          494.0
        ],
        [
          537.0,
          494.0
        ],
        [
          576.0,
          518.0
        ],
        [
          562.0,
          530.0
        ],
        [
          566.0,
          581.0
        ],
        [
          570.0,
          558.0
        ],
        [
          578.0,
          583.0
        ],
        [
          618.0,
          586.0
        ],
        [
          638.0,
          599.0
        ],
        [
          654.0,
          596.0
        ],
        [
          650.0,
          568.0
        ],
        [
          630.0,
          549.0
        ],
        [
          618.0,
          546.0
        ],
        [
          610.0,
          533.0
        ],
        [
          612.0,
          518.0
        ],
        [
          633.0,
          494.0
        ],
        [
          635.0,
          431.0
        ],
        [
          642.0,
          416.0
        ],
        [
          648.0,
          422.0
        ],
        [
          648.0,
          446.0
        ],
        [
          656.0,
          451.0
        ],
        [
          646.0,
          459.0
        ],
        [
          649.0,
          486.0
        ],
        [
          684.0,
          473.0
        ],
        [
          691.0,
          461.0
        ],
        [
          709.0,
          513.0
        ],
        [
          732.0,
          542.0
        ],
        [
          786.0,
          553.0
        ],
        [
          803.0,
          568.0
        ],
        [
          806.0,
          589.0
        ],
        [
          806.0,
          577.0
        ],
        [
          817.0,
          572.0
        ],
        [
          829.0,
          578.0
        ],
        [
          829.0,
          585.0
        ],
        [
          832.0,
          577.0
        ],
        [
          859.0,
          574.0
        ],
        [
          866.0,
          583.0
        ],
        [
          865.0,
          564.0
        ],
        [
          858.0,
          569.0
        ],
        [
          853.0,
          562.0
        ],
        [
          840.0,
          560.0
        ],
        [
          839.0,
          547.0
        ],
        [
          852.0,
          542.0
        ],
        [
          841.0,
          539.0
        ],
        [
          839.0,
          531.0
        ],
        [
          859.0,
          518.0
        ],
        [
          876.0,
          518.0
        ],
        [
          867.0,
          500.0
        ],
        [
          877.0,
          497.0
        ],
        [
          879.0,
          470.0
        ],
        [
          894.0,
          454.0
        ],
        [
          890.0,
          361.0
        ],
        [
          881.0,
          350.0
        ],
        [
          887.0,
          349.0
        ],
        [
          887.0,
          339.0
        ],
        [
          871.0,
          336.0
        ],
        [
          864.0,
          325.0
        ],
        [
          828.0,
          304.0
        ],
        [
          854.0,
          236.0
        ]
      ],
      "group_id": null,
      "shape_type": "polygon",
      "flags": {}
    },
    {
      "label": "4",
      "text": "",
      "points": [
        [
          913.0,
          191.0
        ],
        [
          902.0,
          194.0
        ],
        [
          890.0,
          204.0
        ],
        [
          884.0,
          217.0
        ],
        [
          863.0,
          225.0
        ],
        [
          858.0,
          229.0
        ],
        [
          856.0,
          234.0
        ],
        [
          855.0,
          248.0
        ],
        [
          850.0,
          258.0
        ],
        [
          849.0,
          274.0
        ],
        [
          851.0,
          282.0
        ],
        [
          856.0,
          290.0
        ],
        [
          861.0,
          316.0
        ],
        [
          871.0,
          324.0
        ],
        [
          888.0,
          327.0
        ],
        [
          897.0,
          338.0
        ],
        [
          899.0,
          369.0
        ],
        [
          894.0,
          410.0
        ],
        [
          896.0,
          418.0
        ],
        [
          901.0,
          423.0
        ],
        [
          906.0,
          422.0
        ],
        [
          908.0,
          424.0
        ],
        [
          908.0,
          428.0
        ],
        [
          905.0,
          431.0
        ],
        [
          901.0,
          431.0
        ],
        [
          900.0,
          433.0
        ],
        [
          902.0,
          446.0
        ],
        [
          897.0,
          473.0
        ],
        [
          898.0,
          572.0
        ],
        [
          893.0,
          584.0
        ],
        [
          908.0,
          585.0
        ],
        [
          913.0,
          587.0
        ],
        [
          926.0,
          587.0
        ],
        [
          944.0,
          597.0
        ],
        [
          961.0,
          602.0
        ],
        [
          969.0,
          598.0
        ],
        [
          981.0,
          587.0
        ],
        [
          1002.0,
          576.0
        ],
        [
          1017.0,
          573.0
        ],
        [
          1020.0,
          570.0
        ],
        [
          1021.0,
          333.0
        ],
        [
          1019.0,
          326.0
        ],
        [
          1013.0,
          323.0
        ],
        [
          1013.0,
          318.0
        ],
        [
          1019.0,
          308.0
        ],
        [
          1019.0,
          277.0
        ],
        [
          1021.0,
          268.0
        ],
        [
          1021.0,
          255.0
        ],
        [
          1019.0,
          250.0
        ],
        [
          1006.0,
          251.0
        ],
        [
          997.0,
          244.0
        ],
        [
          998.0,
          231.0
        ],
        [
          1003.0,
          224.0
        ],
        [
          1003.0,
          219.0
        ],
        [
          1006.0,
          215.0
        ],
        [
          1006.0,
          209.0
        ],
        [
          998.0,
          197.0
        ],
        [
          994.0,
          194.0
        ],
        [
          988.0,
          192.0
        ],
        [
          971.0,
          192.0
        ],
        [
          961.0,
          194.0
        ],
        [
          944.0,
          211.0
        ],
        [
          941.0,
          211.0
        ],
        [
          931.0,
          195.0
        ],
        [
          925.0,
          192.0
        ]
      ],
      "group_id": null,
      "shape_type": "polygon",
      "flags": {}
    },
    {
      "label": "4",
      "text": "",
      "points": [
        [
          280.0,
          216.0
        ],
        [
          268.0,
          222.0
        ],
        [
          259.0,
          235.0
        ],
        [
          255.0,
          266.0
        ],
        [
          257.0,
          283.0
        ],
        [
          272.0,
          284.0
        ],
        [
          291.0,
          292.0
        ],
        [
          298.0,
          284.0
        ],
        [
          298.0,
          275.0
        ],
        [
          288.0,
          268.0
        ],
        [
          288.0,
          252.0
        ],
        [
          291.0,
          251.0
        ],
        [
          305.0,
          278.0
        ],
        [
          307.0,
          293.0
        ],
        [
          299.0,
          301.0
        ],
        [
          310.0,
          323.0
        ],
        [
          314.0,
          339.0
        ],
        [
          308.0,
          369.0
        ],
        [
          303.0,
          376.0
        ],
        [
          300.0,
          391.0
        ],
        [
          295.0,
          397.0
        ],
        [
          300.0,
          416.0
        ],
        [
          300.0,
          458.0
        ],
        [
          307.0,
          506.0
        ],
        [
          302.0,
          531.0
        ],
        [
          306.0,
          537.0
        ],
        [
          302.0,
          542.0
        ],
        [
          295.0,
          594.0
        ],
        [
          287.0,
          614.0
        ],
        [
          287.0,
          655.0
        ],
        [
          283.0,
          683.0
        ],
        [
          284.0,
          694.0
        ],
        [
          289.0,
          684.0
        ],
        [
          296.0,
          684.0
        ],
        [
          298.0,
          695.0
        ],
        [
          304.0,
          704.0
        ],
        [
          306.0,
          729.0
        ],
        [
          304.0,
          739.0
        ],
        [
          301.0,
          742.0
        ],
        [
          296.0,
          736.0
        ],
        [
          291.0,
          736.0
        ],
        [
          278.0,
          750.0
        ],
        [
          275.0,
          760.0
        ],
        [
          277.0,
          763.0
        ],
        [
          285.0,
          763.0
        ],
        [
          292.0,
          759.0
        ],
        [
          327.0,
          753.0
        ],
        [
          336.0,
          740.0
        ],
        [
          344.0,
          734.0
        ],
        [
          346.0,
          717.0
        ],
        [
          349.0,
          714.0
        ],
        [
          355.0,
          717.0
        ],
        [
          362.0,
          714.0
        ],
        [
          365.0,
          718.0
        ],
        [
          366.0,
          732.0
        ],
        [
          371.0,
          741.0
        ],
        [
          373.0,
          761.0
        ],
        [
          397.0,
          762.0
        ],
        [
          404.0,
          754.0
        ],
        [
          406.0,
          747.0
        ],
        [
          404.0,
          682.0
        ],
        [
          406.0,
          565.0
        ],
        [
          398.0,
          494.0
        ],
        [
          393.0,
          513.0
        ],
        [
          390.0,
          513.0
        ],
        [
          388.0,
          422.0
        ],
        [
          380.0,
          416.0
        ],
        [
          376.0,
          402.0
        ],
        [
          381.0,
          386.0
        ],
        [
          392.0,
          374.0
        ],
        [
          399.0,
          350.0
        ],
        [
          418.0,
          330.0
        ],
        [
          419.0,
          316.0
        ],
        [
          416.0,
          302.0
        ],
        [
          424.0,
          296.0
        ],
        [
          426.0,
          261.0
        ],
        [
          421.0,
          247.0
        ],
        [
          417.0,
          262.0
        ],
        [
          413.0,
          264.0
        ],
        [
          408.0,
          260.0
        ],
        [
          408.0,
          247.0
        ],
        [
          411.0,
          242.0
        ],
        [
          405.0,
          239.0
        ],
        [
          387.0,
          243.0
        ],
        [
          383.0,
          249.0
        ],
        [
          383.0,
          277.0
        ],
        [
          379.0,
          283.0
        ],
        [
          373.0,
          274.0
        ],
        [
          346.0,
          269.0
        ],
        [
          342.0,
          261.0
        ],
        [
          345.0,
          250.0
        ],
        [
          344.0,
          235.0
        ],
        [
          339.0,
          227.0
        ],
        [
          325.0,
          222.0
        ],
        [
          307.0,
          229.0
        ],
        [
          298.0,
          222.0
        ]
      ],
      "group_id": null,
      "shape_type": "polygon",
      "flags": {}
    }
  ],
  "imagePath": "2 (1).png",
  "imageData": null,
  "imageHeight": 1024,
  "imageWidth": 1024,
  "text": ""
}